sleuth.py
sleuth_mock-0.1.dist-info/LICENSE
sleuth_mock-0.1.dist-info/METADATA
sleuth_mock-0.1.dist-info/WHEEL
sleuth_mock-0.1.dist-info/top_level.txt
sleuth_mock-0.1.dist-info/RECORD
