Metadata-Version: 2.1
Name: sleuth-mock
Version: 0.1
Summary: A minimal Python mocking library
Home-page: https://github.com/kazade/sleuth
Author: Luke Benstead
Author-email: kazade@gmail.com
License: UNKNOWN
Keywords: python,mock,testing,test,unittest,monkeypatch,patch,stub
Platform: UNKNOWN
